MANIFEST.in
README.md
requirements.txt
setup.py
Garen.egg-info/PKG-INFO
Garen.egg-info/SOURCES.txt
Garen.egg-info/dependency_links.txt
Garen.egg-info/top_level.txt
src/Garen.py
src/__init__.py