Metadata-Version: 1.2
Name: Garen
Version: 0.0.13
Summary: # garan
